<?xml version="1.0" encoding="utf-8"?><HelpTOCNode Title="Solve Method " Url="html/21bdf80d-c2a5-69a0-c07b-ab6343d42675.htm"><HelpTOCNode Title="Solve(T) Method (T[,])" Url="html/52eff918-a08a-4df3-8767-08dce24d06eb.htm" /><HelpTOCNode Title="Solve(T) Method (T[,], Func(T, Boolean))" Url="html/5cf63d59-cee1-346a-60b5-713afc4847bf.htm" /><HelpTOCNode Title="Solve(T) Method (T[,], Int32)" Url="html/db6ec211-e9a4-e48d-ada5-6cbd2349cdda.htm" /><HelpTOCNode Title="Solve(T) Method (T[,], Func(T, Boolean), Int32)" Url="html/3515f846-3fc9-9403-2e3a-a395a6f66823.htm" /><HelpTOCNode Title="Solve(TData, TRow, TCol) Method (TData, Func(TData, IEnumerable(TRow)), Func(TRow, IEnumerable(TCol)))" Url="html/441bd34e-a4ae-52a7-1050-6f150ca10978.htm" /><HelpTOCNode Title="Solve(TData, TRow, TCol) Method (TData, Func(TData, IEnumerable(TRow)), Func(TRow, IEnumerable(TCol)), Func(TCol, Boolean))" Url="html/1d11be46-043c-c85b-16cb-844208bd31f5.htm" /><HelpTOCNode Title="Solve(TData, TRow, TCol) Method (TData, Func(TData, IEnumerable(TRow)), Func(TRow, IEnumerable(TCol)), Int32)" Url="html/f5dceaef-f723-35f9-78b0-c70b2a180481.htm" /><HelpTOCNode Title="Solve(TData, TRow, TCol) Method (TData, Func(TData, IEnumerable(TRow)), Func(TRow, IEnumerable(TCol)), Func(TCol, Boolean), Int32)" Url="html/f40a0e93-d73a-6f89-4bdd-d000982bfdaa.htm" /></HelpTOCNode>